bprofanity/__init__.py
bprofanity/bprofanity.py
bprofanity/data/wordlist.enc
bprofanity-0.5.data/data/data/wordlist.enc
bprofanity-0.5.dist-info/LICENSE
bprofanity-0.5.dist-info/METADATA
bprofanity-0.5.dist-info/WHEEL
bprofanity-0.5.dist-info/top_level.txt
bprofanity-0.5.dist-info/RECORD
